Tarea_3/src/design/multiplicador.sv
//Contador de anillo filas
//******************************
//******************************
module anillo_ctdr #(parameter WIDTH = 4) //Se define el tamano del contador 4.
(
    input clk,
    input rst,
    output reg [WIDTH-1:0] fila
);

always_ff @(posedge clk) begin
    if (!rst)
        fila <=1; //Se inicializa encendiendo el primer bit.
    else begin
        fila[WIDTH-1] <= fila[0];
        for (int i = 0; i < WIDTH-1; i=i+1 ) begin  //Es un shifter
            fila[i] <= fila[i+1];
        end
    end
end
endmodule


//Detector de teclas con FSM.
//*************************************
//*************************************
module detector_columna (
    input logic clk,
    input logic rst,
    input logic [3:0]fila,  //entrada de contador de anillo;
    
    //entradas fisicas a FPGA
    input logic col_0, 
    input logic col_1, 
    input logic col_2, 
    input logic col_3, 

    output logic [3:0]tecla_pre,    //salida de teclas en bits.
    output logic menos,             //salida de codigo de signo menos.
    output logic multiplicador,       //salida de multiplicador. 
    output logic igual              //salida de codigo de igual.
);

    //se definen estados de la FSM
    typedef enum logic [4:0] { 
        F0, F1 , F2, F3, 
        F0C0, F0C1, F0C2, F0C3,
        F1C0, F1C1, F1C2, F1C3,
        F2C0, F2C1, F2C2, F2C3,
        F3C0, F3C1, F3C2, F3C3
    } estado;

    estado estado_act, estado_sig;
    logic [3:0] salida;

    //Para el estado actual
    always_ff @(posedge clk or posedge rst)begin
        if (rst)begin
            estado_act <= F0; //estado de espera
        end 
        else begin
            estado_act <= estado_sig;
        end
    end

    //Logica combinacional de la FSM, entre los estados
    always_comb begin
        estado_sig = estado_act; //Estado por defecto
        case(estado_act)

            //Primero verifica si la fila esta activa, si no pasa a la otra
            //Si esta activa, depende de cual col este activa, se da el siguiente estado
            F0: begin
                if(fila == 4'b0001) begin
                    if (col_0) estado_sig = F0C0; 
                    else if (col_1) estado_sig = F0C1;
                    else if (col_2) estado_sig = F0C2;
                    else if (col_3) estado_sig = F0C3;
                    else estado_sig = F1;
                end
                else begin 
                    estado_sig = F1;
                end
            end
            F1: begin
                if (fila == 4'b0010)begin
                    if (col_0) estado_sig = F1C0;
                    else if (col_1) estado_sig = F1C1;
                    else if (col_2) estado_sig = F1C2;
                    else if (col_3) estado_sig = F1C3;
                    else estado_sig = F2;
                end
                else begin 
                    estado_sig = F2;
                end
            end
            F2: begin
                if(fila == 4'b0100) begin
                    if (col_0) estado_sig = F2C0;
                    else if (col_1) estado_sig = F2C1;
                    else if (col_2) estado_sig = F2C2;
                    else if (col_3) estado_sig = F2C3;
                    else estado_sig = F3;
                end
                else begin 
                    estado_sig = F3;
                end
            end
            F3: begin
                if (fila == 4'b1000)begin
                    if (col_0) estado_sig = F3C0;
                    else if (col_1) estado_sig = F3C1;
                    else if (col_2) estado_sig = F3C2;
                    else if (col_3) estado_sig = F3C3;
                    else estado_sig = F0;
                end
                else begin 
                    estado_sig = F0;
                end
            end
            default: estado_sig = F0;
        endcase     
    end 

    //Detectar estado y asignar codigo binario al estado para saber las teclas en binario
    always_ff @(posedge clk or posedge rst) begin 
        if (rst)begin 
            salida <= 4'b0000;
        end
        else begin
            case (estado_act)
                F0C0: salida <= 4'b0000; //1
                F0C1: salida <= 4'b0001; //2
                F0C2: salida <= 4'b0010; //3
                F0C3: salida <= 4'b0011; //A  (menos)
                F1C0: salida <= 4'b0100; //4
                F1C1: salida <= 4'b0101; //5
                F1C2: salida <= 4'b0110; //6
                F1C3: salida <= 4'b0111; //B  (multiplicador)
                F2C0: salida <= 4'b1000; //7
                F2C1: salida <= 4'b1001; //8
                F2C2: salida <= 4'b1010; //9
                F2C3: salida <= 4'b1011; //C  (igual)
                F3C0: salida <= 4'b1100; //E
                F3C1: salida <= 4'b1101; //0
                F3C2: salida <= 4'b1110; //F
                F3C3: salida <= 4'b1111; //D
                default: salida <= 4'b0000;
            endcase
        end
    end

    //asigna la salida
    assign tecla_pre = salida;
    //se activa el menos

    always_comb begin
        menos = (salida == 4'b0011);
        multiplicador = (salida == 4'b0111);
        igual = (salida == 4'b1011);
    end

endmodule



// divisor de clk
//*******************************
//*******************************
module divisor (
    input logic clk,
    output reg clk_div
);

    parameter frecuencia = 27000000; //27 Mhz
    parameter fre = 1000000; //10hz
    parameter max_cuenta = frecuencia / (2*fre); //13.5 ciclos aprox 

    reg [4:0]cuenta;

    initial begin 
        cuenta = 0;
        clk_div = 0;
    end
    always_ff @(posedge clk) begin 
        if (cuenta == max_cuenta) begin //la cantidad de ciclos en alto o bajo
            clk_div <= ~clk_div;
            cuenta <= 0;
        end
        else begin
            cuenta <= cuenta+1;
        end
    end
endmodule


// Rebote mecanico
//****************************
//****************************
module rebote(
    input logic clk,
    input logic boton,
    output logic boton_sal
); 
    logic clk_hab;
    //Salidas de FF D, Q2_com es el complemento.
    logic q1, q2, q2_com, q0;

    divisor clk_ha( clk, clk_hab);

    FF_D_habilitador ff1(clk, clk_hab, boton, q0);
    FF_D_habilitador ff2(clk, clk_hab, q0, q1);
    FF_D_habilitador ff3(clk, clk_hab, q1, q2);

    assign q2_com = ~q2;
    assign boton_sal = q1 & q2_com; //AND para salida
endmodule


//FF_D se actualiza cuando clk_hab esta en alto.
module FF_D_habilitador(
    input logic clk, 
    input logic clk_hab,
    input logic D, 
    output reg Q=0
);
    always_ff @ (posedge clk) begin
        if(clk_hab == 1) 
            Q <= D;
    end
endmodule 


//Almacenamiento
//**********************************
//**********************************
module almacenamiento(
    input logic clk,
    input logic rst,
    input logic almac,
    input logic [3:0] num1_dec1,   // Primer número de 4 bits para numero1
    input logic [3:0] num1_dec2,   // Segundo número de 4 bits para numero1
    input logic [3:0] num2_dec1,   // Primer número de 4 bits para numero2
    input logic [3:0] num2_dec2,   // Segundo número de 4 bits para numero2
    output logic [11:0] num_result1,  // Resultado de la concatenación de num1
    output logic [11:0] num_result2   // Resultado de la concatenación de num2
);

    always_ff @(posedge clk or posedge rst) begin
        if (rst) begin
            num_result1 <= 12'b0;
            num_result2 <= 12'b0;
        end else if (almac) begin
            // Concatenar los números de 4 bits y almacenarlos
            num_result1 <= {num1_dec1, num1_dec2}; // Concatenación de num1_dec1 y num1_dec2
            num_result2 <= {num2_dec1, num2_dec2}; // Concatenación de num2_dec1 y num2_dec2
        end
    end

endmodule


//Separador de numeros
//*****************************************
//*****************************************
module separar_num (
    input logic [13:0] num,
    output logic [3:0] uni, dec, cen, mill
);

logic [3:0] bcd_uni, bcd_dec, bcd_cen, bcd_mill;
integer i;

always_comb begin
    // Inicializar todas las variables a 0
    bcd_uni = 0;
    bcd_dec = 0;
    bcd_cen = 0;
    bcd_mill = 0;

    for (i = 13; i >= 0; i = i - 1) begin
        // Revisar y ajustar cada grupo de 4 bits antes de desplazar
        if (bcd_uni >= 5) bcd_uni = bcd_uni + 3;
        if (bcd_dec >= 5) bcd_dec = bcd_dec + 3;
        if (bcd_cen >= 5) bcd_cen = bcd_cen + 3;
        if (bcd_mill >= 5) bcd_mill = bcd_mill + 3;

        // Desplazamiento manualmente de los bits
        bcd_mill = {bcd_mill[2:0], bcd_cen[3]};
        bcd_cen = {bcd_cen[2:0], bcd_dec[3]};
        bcd_dec = {bcd_dec[2:0], bcd_uni[3]};
        bcd_uni = {bcd_uni[2:0], num[i]};
    end
end
assign uni = bcd_uni;
assign dec = bcd_dec;
assign cen = bcd_cen;
assign mill = bcd_mill;

endmodule


//Idea 7-seg
//**************************************
//**************************************
`timescale 1ns / 1ps
module display (
    input logic clk,
    output logic [6:0] Seg,
    output logic [3:0] anodes,
    input logic [15:0] result
);

    logic [6:0] number;
    logic [3:0] state = 4'b0000; // Inicialización del estado
    logic [15:0] data;
    logic [3:0] dig;
    logic slow_clock = 0;
    integer count = 0;

    assign data = result;

    // Generador de reloj lento
    always_ff @(posedge clk) begin
        if (count > 2) begin// cambiar count > 100000 al probar la fpga
            count <= 0;
            slow_clock <= ~slow_clock;
        end else begin
            count <= count + 1;
        end
    end

    // Control de anodos y segmentos
    always_ff @(posedge slow_clock) begin
        case (state)
            4'b0000: begin
                anodes = 4'b1110;
                state = 4'b0001;
                dig = data[3:0];
            end
            4'b0001: begin
                anodes = 4'b1101;
                state = 4'b0010;
                dig = data[7:4];
            end
            4'b0010: begin
                anodes = 4'b1011;
                state = 4'b0011;
                dig = data[11:8];
            end
            4'b0011: begin
                anodes = 4'b0111;
                state = 4'b0000;
                dig = data[15:12];
            end
        endcase

        case (dig)
            4'b0000: number = 7'b1000000; // 0
            4'b0001: number = 7'b1111001; // 1
            4'b0010: number = 7'b0100100; // 2
            4'b0011: number = 7'b0110000; // 3
            4'b0100: number = 7'b0011001; // 4
            4'b0101: number = 7'b0010010; // 5
            4'b0110: number = 7'b0000010; // 6
            4'b0111: number = 7'b1111000; // 7
            4'b1000: number = 7'b0000000; // 8
            4'b1001: number = 7'b0011000; // 9
            4'b1010: number = 7'b0001000; // A
            4'b1011: number = 7'b0000011; // B
            4'b1100: number = 7'b1000110; // C
            4'b1101: number = 7'b0100001; // D
            4'b1110: number = 7'b0000110; // E
            4'b1111: number = 7'b0001110; // F
            default: number = 7'b0000000; // Apagado
        endcase
    end

    assign Seg = number;

endmodule


// Modulo de multiplicador
//*************************
//*************************
module multiplicador(
    input  logic [7:0] A, // Primer número de dos dígitos
    input  logic [7:0] B, // Segundo número de dos dígitos
    input  logic clk,     // Señal de reloj
    input  logic start,   // Señal para comenzar la multiplicación
    output logic [15:0] resultado, // Resultado de la multiplicación
    output logic done    // Indica cuando la multiplicación ha terminado
);
    logic [15:0] acumulador;
    logic [7:0] contador;
    logic [7:0] multiplicando;
    logic [7:0] multiplicador;
    logic busy;

    always_ff @(posedge clk) begin
        if (start) begin
            // Inicializamos los valores
            acumulador <= 16'd0;
            multiplicando <= A;
            multiplicador <= B;
            contador <= 8'd0;
            busy <= 1;
            done <= 0;
        end else if (busy) begin
            if (contador < multiplicador) begin
                acumulador <= acumulador + multiplicando;
                contador <= contador + 1;
            end else begin
                resultado <= acumulador;
                done <= 1;
                busy <= 0;
            end
        end
    end

endmodule


//Modulo del BCD
//****************************************
//****************************************
//Para dividir los numeros esteros
module codificador_bcd (
    input  logic        clk,          // Reloj de entrada
    input  logic [15:0] binary_in,    // Entrada binaria de 16 bits
    output logic [15:0] bcd_out       // Salida BCD de 16 bits
);
    // Variables internas
    logic [31:0] shift_reg;  // Registro de desplazamiento (16 bits BCD + 16 bits binarios)
    int state;               // Estado del contador para controlar las iteraciones

    always_ff @(posedge clk) begin
        if (state == 0) begin
            // Inicializar el registro de desplazamiento y contador
            shift_reg = {16'b0, binary_in};  // Concatenar 16 bits de ceros y la entrada binaria
            state = 1;  // Ir al primer estado
        end else if (state <= 16) begin
            // Algoritmo "Double Dabble" paso a paso
            for (int j = 0; j < 4; j++) begin
                if (shift_reg[19 + 4*j -: 4] >= 5) begin
                    shift_reg[19 + 4*j -: 4] += 3;
                end
            end
            shift_reg = shift_reg << 1;  // Desplazar a la izquierda
            state = state + 1;           // Incrementar estado
        end else begin
            // Asignar la salida BCD cuando el proceso termine
            bcd_out = shift_reg[31:16];
            state = 0;  // Reiniciar el estado para la próxima operación
        end
    end
endmodule

Tarea_3/src/sim/codificador_bcd_tb.sv
`timescale 1ns / 1ps
//////////////////////////////////////////////////////////////////////////////////
// Company: 
// Engineer: 

module codificador_bcd_tb();

    logic [15:0] binary_in;
    logic [15:0] bcd_out;
    logic clk;
    codificador_bcd DUT(
        .clk(clk),
        .binary_in(binary_in),
        .bcd_out(bcd_out));


    // Inicialización de las entradas
   initial begin
   clk = 0;
   forever #1 clk = ~clk;
   end 
    initial begin
        clk = 0; // Inicialmente, el reloj está en bajo
        binary_in = 16'd1234;
        #1000;
        
        $finish; // Finalizar la simulación después de realizar las pruebas
    end
        // Para el diagrama de tiempos
    initial begin 
        $dumpfile("codificador_bcd_tb.vcd");
        $dumpvars(0, codificador_bcd_tb); 
    end
endmodule

Tarea_3/src/build/codificador_bcd_tb.vcd
$date
	Mon Nov 18 04:15:42 2024
$end
$version
	Icarus Verilog
$end
$timescale
	1ps
$end
$scope module codificador_bcd_tb $end
$var wire 16 ! bcd_out [15:0] $end
$var reg 16 " binary_in [15:0] $end
$var reg 1 # clk $end
$scope module DUT $end
$var wire 16 $ binary_in [15:0] $end
$var wire 1 # clk $end
$var reg 16 % bcd_out [15:0] $end
$var reg 32 & shift_reg [31:0] $end
$var integer 32 ' state [31:0] $end
$scope begin $ivl_for_loop1 $end
$var integer 32 ( j [31:0] $end
$upscope $end
$upscope $end
$upscope $end
$enddefinitions $end
$comment Show the parameter values. $end
$dumpall
$end
#0
$dumpvars
b0 (
b0 '
bx &
bx %
b10011010010 $
0#
b10011010010 "
bx !
$end
#1000
b1 '
b10011010010 &
1#
#2000
0#
#3000
b10 '
b100110100100 &
b100 (
1#
#4000
0#
#5000
b11 '
b1001101001000 &
b100 (
1#
#6000
0#
#7000
b100 '
b10011010010000 &
b100 (
1#
#8000
0#
#9000
b101 '
b100110100100000 &
b100 (
1#
#10000
0#
#11000
b110 '
b1001101001000000 &
b100 (
1#
#12000
0#
#13000
b111 '
b10011010010000000 &
b100 (
1#
#14000
0#
#15000
b1000 '
b100110100100000000 &
b100 (
1#
#16000
0#
#17000
b1001 '
b1001101001000000000 &
b100 (
1#
#18000
0#
#19000
b1010 '
b10011010010000000000 &
b100 (
1#
#20000
0#
#21000
b1011 '
b110010100100000000000 &
b100 (
1#
#22000
0#
#23000
b1100 '
b1110001001000000000000 &
b100 (
1#
#24000
0#
#25000
b1101 '
b11101110010000000000000 &
b100 (
1#
#26000
0#
#27000
b1110 '
b1010101000100000000000000 &
b100 (
1#
#28000
0#
#29000
b1111 '
b11000010001000000000000000 &
b100 (
1#
#30000
0#
#31000
b10000 '
b110000101110000000000000000 &
b100 (
1#
#32000
0#
#33000
b10001 '
b10010001101000000000000000000 &
b100 (
1#
#34000
0#
#35000
b0 '
b1001000110100 !
b1001000110100 %
1#
#36000
0#
#37000
b1 '
b10011010010 &
1#
#38000
0#
#39000
b10 '
b100110100100 &
b100 (
1#
#40000
0#
#41000
b11 '
b1001101001000 &
b100 (
1#
#42000
0#
#43000
b100 '
b10011010010000 &
b100 (
1#
#44000
0#
#45000
b101 '
b100110100100000 &
b100 (
1#
#46000
0#
#47000
b110 '
b1001101001000000 &
b100 (
1#
#48000
0#
#49000
b111 '
b10011010010000000 &
b100 (
1#
#50000
0#
#51000
b1000 '
b100110100100000000 &
b100 (
1#
#52000
0#
#53000
b1001 '
b1001101001000000000 &
b100 (
1#
#54000
0#
#55000
b1010 '
b10011010010000000000 &
b100 (
1#
#56000
0#
#57000
b1011 '
b110010100100000000000 &
b100 (
1#
#58000
0#
#59000
b1100 '
b1110001001000000000000 &
b100 (
1#
#60000
0#
#61000
b1101 '
b11101110010000000000000 &
b100 (
1#
#62000
0#
#63000
b1110 '
b1010101000100000000000000 &
b100 (
1#
#64000
0#
#65000
b1111 '
b11000010001000000000000000 &
b100 (
1#
#66000
0#
#67000
b10000 '
b110000101110000000000000000 &
b100 (
1#
#68000
0#
#69000
b10001 '
b10010001101000000000000000000 &
b100 (
1#
#70000
0#
#71000
b0 '
1#
#72000
0#
#73000
b1 '
b10011010010 &
1#
#74000
0#
#75000
b10 '
b100110100100 &
b100 (
1#
#76000
0#
#77000
b11 '
b1001101001000 &
b100 (
1#
#78000
0#
#79000
b100 '
b10011010010000 &
b100 (
1#
#80000
0#
#81000
b101 '
b100110100100000 &
b100 (
1#
#82000
0#
#83000
b110 '
b1001101001000000 &
b100 (
1#
#84000
0#
#85000
b111 '
b10011010010000000 &
b100 (
1#
#86000
0#
#87000
b1000 '
b100110100100000000 &
b100 (
1#
#88000
0#
#89000
b1001 '
b1001101001000000000 &
b100 (
1#
#90000
0#
#91000
b1010 '
b10011010010000000000 &
b100 (
1#
#92000
0#
#93000
b1011 '
b110010100100000000000 &
b100 (
1#
#94000
0#
#95000
b1100 '
b1110001001000000000000 &
b100 (
1#
#96000
0#
#97000
b1101 '
b11101110010000000000000 &
b100 (
1#
#98000
0#
#99000
b1110 '
b1010101000100000000000000 &
b100 (
1#
#100000
0#
#101000
b1111 '
b11000010001000000000000000 &
b100 (
1#
#102000
0#
#103000
b10000 '
b110000101110000000000000000 &
b100 (
1#
#104000
0#
#105000
b10001 '
b10010001101000000000000000000 &
b100 (
1#
#106000
0#
#107000
b0 '
1#
#108000
0#
#109000
b1 '
b10011010010 &
1#
#110000
0#
#111000
b10 '
b100110100100 &
b100 (
1#
#112000
0#
#113000
b11 '
b1001101001000 &
b100 (
1#
#114000
0#
#115000
b100 '
b10011010010000 &
b100 (
1#
#116000
0#
#117000
b101 '
b100110100100000 &
b100 (
1#
#118000
0#
#119000
b110 '
b1001101001000000 &
b100 (
1#
#120000
0#
#121000
b111 '
b10011010010000000 &
b100 (
1#
#122000
0#
#123000
b1000 '
b100110100100000000 &
b100 (
1#
#124000
0#
#125000
b1001 '
b1001101001000000000 &
b100 (
1#
#126000
0#
#127000
b1010 '
b10011010010000000000 &
b100 (
1#
#128000
0#
#129000
b1011 '
b110010100100000000000 &
b100 (
1#
#130000
0#
#131000
b1100 '
b1110001001000000000000 &
b100 (
1#
#132000
0#
#133000
b1101 '
b11101110010000000000000 &
b100 (
1#
#134000
0#
#135000
b1110 '
b1010101000100000000000000 &
b100 (
1#
#136000
0#
#137000
b1111 '
b11000010001000000000000000 &
b100 (
1#
#138000
0#
#139000
b10000 '
b110000101110000000000000000 &
b100 (
1#
#140000
0#
#141000
b10001 '
b10010001101000000000000000000 &
b100 (
1#
#142000
0#
#143000
b0 '
1#
#144000
0#
#145000
b1 '
b10011010010 &
1#
#146000
0#
#147000
b10 '
b100110100100 &
b100 (
1#
#148000
0#
#149000
b11 '
b1001101001000 &
b100 (
1#
#150000
0#
#151000
b100 '
b10011010010000 &
b100 (
1#
#152000
0#
#153000
b101 '
b100110100100000 &
b100 (
1#
#154000
0#
#155000
b110 '
b1001101001000000 &
b100 (
1#
#156000
0#
#157000
b111 '
b10011010010000000 &
b100 (
1#
#158000
0#
#159000
b1000 '
b100110100100000000 &
b100 (
1#
#160000
0#
#161000
b1001 '
b1001101001000000000 &
b100 (
1#
#162000
0#
#163000
b1010 '
b10011010010000000000 &
b100 (
1#
#164000
0#
#165000
b1011 '
b110010100100000000000 &
b100 (
1#
#166000
0#
#167000
b1100 '
b1110001001000000000000 &
b100 (
1#
#168000
0#
#169000
b1101 '
b11101110010000000000000 &
b100 (
1#
#170000
0#
#171000
b1110 '
b1010101000100000000000000 &
b100 (
1#
#172000
0#
#173000
b1111 '
b11000010001000000000000000 &
b100 (
1#
#174000
0#
#175000
b10000 '
b110000101110000000000000000 &
b100 (
1#
#176000
0#
#177000
b10001 '
b10010001101000000000000000000 &
b100 (
1#
#178000
0#
#179000
b0 '
1#
#180000
0#
#181000
b1 '
b10011010010 &
1#
#182000
0#
#183000
b10 '
b100110100100 &
b100 (
1#
#184000
0#
#185000
b11 '
b1001101001000 &
b100 (
1#
#186000
0#
#187000
b100 '
b10011010010000 &
b100 (
1#
#188000
0#
#189000
b101 '
b100110100100000 &
b100 (
1#
#190000
0#
#191000
b110 '
b1001101001000000 &
b100 (
1#
#192000
0#
#193000
b111 '
b10011010010000000 &
b100 (
1#
#194000
0#
#195000
b1000 '
b100110100100000000 &
b100 (
1#
#196000
0#
#197000
b1001 '
b1001101001000000000 &
b100 (
1#
#198000
0#
#199000
b1010 '
b10011010010000000000 &
b100 (
1#
#200000
0#
#201000
b1011 '
b110010100100000000000 &
b100 (
1#
#202000
0#
#203000
b1100 '
b1110001001000000000000 &
b100 (
1#
#204000
0#
#205000
b1101 '
b11101110010000000000000 &
b100 (
1#
#206000
0#
#207000
b1110 '
b1010101000100000000000000 &
b100 (
1#
#208000
0#
#209000
b1111 '
b11000010001000000000000000 &
b100 (
1#
#210000
0#
#211000
b10000 '
b110000101110000000000000000 &
b100 (
1#
#212000
0#
#213000
b10001 '
b10010001101000000000000000000 &
b100 (
1#
#214000
0#
#215000
b0 '
1#
#216000
0#
#217000
b1 '
b10011010010 &
1#
#218000
0#
#219000
b10 '
b100110100100 &
b100 (
1#
#220000
0#
#221000
b11 '
b1001101001000 &
b100 (
1#
#222000
0#
#223000
b100 '
b10011010010000 &
b100 (
1#
#224000
0#
#225000
b101 '
b100110100100000 &
b100 (
1#
#226000
0#
#227000
b110 '
b1001101001000000 &
b100 (
1#
#228000
0#
#229000
b111 '
b10011010010000000 &
b100 (
1#
#230000
0#
#231000
b1000 '
b100110100100000000 &
b100 (
1#
#232000
0#
#233000
b1001 '
b1001101001000000000 &
b100 (
1#
#234000
0#
#235000
b1010 '
b10011010010000000000 &
b100 (
1#
#236000
0#
#237000
b1011 '
b110010100100000000000 &
b100 (
1#
#238000
0#
#239000
b1100 '
b1110001001000000000000 &
b100 (
1#
#240000
0#
#241000
b1101 '
b11101110010000000000000 &
b100 (
1#
#242000
0#
#243000
b1110 '
b1010101000100000000000000 &
b100 (
1#
#244000
0#
#245000
b1111 '
b11000010001000000000000000 &
b100 (
1#
#246000
0#
#247000
b10000 '
b110000101110000000000000000 &
b100 (
1#
#248000
0#
#249000
b10001 '
b10010001101000000000000000000 &
b100 (
1#
#250000
0#
#251000
b0 '
1#
#252000
0#
#253000
b1 '
b10011010010 &
1#
#254000
0#
#255000
b10 '
b100110100100 &
b100 (
1#
#256000
0#
#257000
b11 '
b1001101001000 &
b100 (
1#
#258000
0#
#259000
b100 '
b10011010010000 &
b100 (
1#
#260000
0#
#261000
b101 '
b100110100100000 &
b100 (
1#
#262000
0#
#263000
b110 '
b1001101001000000 &
b100 (
1#
#264000
0#
#265000
b111 '
b10011010010000000 &
b100 (
1#
#266000
0#
#267000
b1000 '
b100110100100000000 &
b100 (
1#
#268000
0#
#269000
b1001 '
b1001101001000000000 &
b100 (
1#
#270000
0#
#271000
b1010 '
b10011010010000000000 &
b100 (
1#
#272000
0#
#273000
b1011 '
b110010100100000000000 &
b100 (
1#
#274000
0#
#275000
b1100 '
b1110001001000000000000 &
b100 (
1#
#276000
0#
#277000
b1101 '
b11101110010000000000000 &
b100 (
1#
#278000
0#
#279000
b1110 '
b1010101000100000000000000 &
b100 (
1#
#280000
0#
#281000
b1111 '
b11000010001000000000000000 &
b100 (
1#
#282000
0#
#283000
b10000 '
b110000101110000000000000000 &
b100 (
1#
#284000
0#
#285000
b10001 '
b10010001101000000000000000000 &
b100 (
1#
#286000
0#
#287000
b0 '
1#
#288000
0#
#289000
b1 '
b10011010010 &
1#
#290000
0#
#291000
b10 '
b100110100100 &
b100 (
1#
#292000
0#
#293000
b11 '
b1001101001000 &
b100 (
1#
#294000
0#
#295000
b100 '
b10011010010000 &
b100 (
1#
#296000
0#
#297000
b101 '
b100110100100000 &
b100 (
1#
#298000
0#
#299000
b110 '
b1001101001000000 &
b100 (
1#
#300000
0#
#301000
b111 '
b10011010010000000 &
b100 (
1#
#302000
0#
#303000
b1000 '
b100110100100000000 &
b100 (
1#
#304000
0#
#305000
b1001 '
b1001101001000000000 &
b100 (
1#
#306000
0#
#307000
b1010 '
b10011010010000000000 &
b100 (
1#
#308000
0#
#309000
b1011 '
b110010100100000000000 &
b100 (
1#
#310000
0#
#311000
b1100 '
b1110001001000000000000 &
b100 (
1#
#312000
0#
#313000
b1101 '
b11101110010000000000000 &
b100 (
1#
#314000
0#
#315000
b1110 '
b1010101000100000000000000 &
b100 (
1#
#316000
0#
#317000
b1111 '
b11000010001000000000000000 &
b100 (
1#
#318000
0#
#319000
b10000 '
b110000101110000000000000000 &
b100 (
1#
#320000
0#
#321000
b10001 '
b10010001101000000000000000000 &
b100 (
1#
#322000
0#
#323000
b0 '
1#
#324000
0#
#325000
b1 '
b10011010010 &
1#
#326000
0#
#327000
b10 '
b100110100100 &
b100 (
1#
#328000
0#
#329000
b11 '
b1001101001000 &
b100 (
1#
#330000
0#
#331000
b100 '
b10011010010000 &
b100 (
1#
#332000
0#
#333000
b101 '
b100110100100000 &
b100 (
1#
#334000
0#
#335000
b110 '
b1001101001000000 &
b100 (
1#
#336000
0#
#337000
b111 '
b10011010010000000 &
b100 (
1#
#338000
0#
#339000
b1000 '
b100110100100000000 &
b100 (
1#
#340000
0#
#341000
b1001 '
b1001101001000000000 &
b100 (
1#
#342000
0#
#343000
b1010 '
b10011010010000000000 &
b100 (
1#
#344000
0#
#345000
b1011 '
b110010100100000000000 &
b100 (
1#
#346000
0#
#347000
b1100 '
b1110001001000000000000 &
b100 (
1#
#348000
0#
#349000
b1101 '
b11101110010000000000000 &
b100 (
1#
#350000
0#
#351000
b1110 '
b1010101000100000000000000 &
b100 (
1#
#352000
0#
#353000
b1111 '
b11000010001000000000000000 &
b100 (
1#
#354000
0#
#355000
b10000 '
b110000101110000000000000000 &
b100 (
1#
#356000
0#
#357000
b10001 '
b10010001101000000000000000000 &
b100 (
1#
#358000
0#
#359000
b0 '
1#
#360000
0#
#361000
b1 '
b10011010010 &
1#
#362000
0#
#363000
b10 '
b100110100100 &
b100 (
1#
#364000
0#
#365000
b11 '
b1001101001000 &
b100 (
1#
#366000
0#
#367000
b100 '
b10011010010000 &
b100 (
1#
#368000
0#
#369000
b101 '
b100110100100000 &
b100 (
1#
#370000
0#
#371000
b110 '
b1001101001000000 &
b100 (
1#
#372000
0#
#373000
b111 '
b10011010010000000 &
b100 (
1#
#374000
0#
#375000
b1000 '
b100110100100000000 &
b100 (
1#
#376000
0#
#377000
b1001 '
b1001101001000000000 &
b100 (
1#
#378000
0#
#379000
b1010 '
b10011010010000000000 &
b100 (
1#
#380000
0#
#381000
b1011 '
b110010100100000000000 &
b100 (
1#
#382000
0#
#383000
b1100 '
b1110001001000000000000 &
b100 (
1#
#384000
0#
#385000
b1101 '
b11101110010000000000000 &
b100 (
1#
#386000
0#
#387000
b1110 '
b1010101000100000000000000 &
b100 (
1#
#388000
0#
#389000
b1111 '
b11000010001000000000000000 &
b100 (
1#
#390000
0#
#391000
b10000 '
b110000101110000000000000000 &
b100 (
1#
#392000
0#
#393000
b10001 '
b10010001101000000000000000000 &
b100 (
1#
#394000
0#
#395000
b0 '
1#
#396000
0#
#397000
b1 '
b10011010010 &
1#
#398000
0#
#399000
b10 '
b100110100100 &
b100 (
1#
#400000
0#
#401000
b11 '
b1001101001000 &
b100 (
1#
#402000
0#
#403000
b100 '
b10011010010000 &
b100 (
1#
#404000
0#
#405000
b101 '
b100110100100000 &
b100 (
1#
#406000
0#
#407000
b110 '
b1001101001000000 &
b100 (
1#
#408000
0#
#409000
b111 '
b10011010010000000 &
b100 (
1#
#410000
0#
#411000
b1000 '
b100110100100000000 &
b100 (
1#
#412000
0#
#413000
b1001 '
b1001101001000000000 &
b100 (
1#
#414000
0#
#415000
b1010 '
b10011010010000000000 &
b100 (
1#
#416000
0#
#417000
b1011 '
b110010100100000000000 &
b100 (
1#
#418000
0#
#419000
b1100 '
b1110001001000000000000 &
b100 (
1#
#420000
0#
#421000
b1101 '
b11101110010000000000000 &
b100 (
1#
#422000
0#
#423000
b1110 '
b1010101000100000000000000 &
b100 (
1#
#424000
0#
#425000
b1111 '
b11000010001000000000000000 &
b100 (
1#
#426000
0#
#427000
b10000 '
b110000101110000000000000000 &
b100 (
1#
#428000
0#
#429000
b10001 '
b10010001101000000000000000000 &
b100 (
1#
#430000
0#
#431000
b0 '
1#
#432000
0#
#433000
b1 '
b10011010010 &
1#
#434000
0#
#435000
b10 '
b100110100100 &
b100 (
1#
#436000
0#
#437000
b11 '
b1001101001000 &
b100 (
1#
#438000
0#
#439000
b100 '
b10011010010000 &
b100 (
1#
#440000
0#
#441000
b101 '
b100110100100000 &
b100 (
1#
#442000
0#
#443000
b110 '
b1001101001000000 &
b100 (
1#
#444000
0#
#445000
b111 '
b10011010010000000 &
b100 (
1#
#446000
0#
#447000
b1000 '
b100110100100000000 &
b100 (
1#
#448000
0#
#449000
b1001 '
b1001101001000000000 &
b100 (
1#
#450000
0#
#451000
b1010 '
b10011010010000000000 &
b100 (
1#
#452000
0#
#453000
b1011 '
b110010100100000000000 &
b100 (
1#
#454000
0#
#455000
b1100 '
b1110001001000000000000 &
b100 (
1#
#456000
0#
#457000
b1101 '
b11101110010000000000000 &
b100 (
1#
#458000
0#
#459000
b1110 '
b1010101000100000000000000 &
b100 (
1#
#460000
0#
#461000
b1111 '
b11000010001000000000000000 &
b100 (
1#
#462000
0#
#463000
b10000 '
b110000101110000000000000000 &
b100 (
1#
#464000
0#
#465000
b10001 '
b10010001101000000000000000000 &
b100 (
1#
#466000
0#
#467000
b0 '
1#
#468000
0#
#469000
b1 '
b10011010010 &
1#
#470000
0#
#471000
b10 '
b100110100100 &
b100 (
1#
#472000
0#
#473000
b11 '
b1001101001000 &
b100 (
1#
#474000
0#
#475000
b100 '
b10011010010000 &
b100 (
1#
#476000
0#
#477000
b101 '
b100110100100000 &
b100 (
1#
#478000
0#
#479000
b110 '
b1001101001000000 &
b100 (
1#
#480000
0#
#481000
b111 '
b10011010010000000 &
b100 (
1#
#482000
0#
#483000
b1000 '
b100110100100000000 &
b100 (
1#
#484000
0#
#485000
b1001 '
b1001101001000000000 &
b100 (
1#
#486000
0#
#487000
b1010 '
b10011010010000000000 &
b100 (
1#
#488000
0#
#489000
b1011 '
b110010100100000000000 &
b100 (
1#
#490000
0#
#491000
b1100 '
b1110001001000000000000 &
b100 (
1#
#492000
0#
#493000
b1101 '
b11101110010000000000000 &
b100 (
1#
#494000
0#
#495000
b1110 '
b1010101000100000000000000 &
b100 (
1#
#496000
0#
#497000
b1111 '
b11000010001000000000000000 &
b100 (
1#
#498000
0#
#499000
b10000 '
b110000101110000000000000000 &
b100 (
1#
#500000
0#
#501000
b10001 '
b10010001101000000000000000000 &
b100 (
1#
#502000
0#
#503000
b0 '
1#
#504000
0#
