Tarea 2/src/design/module_captura.sv
module general (
    input logic clk;
    input logic rst;
    input logic [0:2] numero1,
    input logic [0:2] numero2,
);
endmodule 

//4.1
module segunda_parte (
    // Segunda parte FSM (Sincronización y Máquina de estado)
    // a tecla para sumar, b tlecla para igualar y c tecla para eliminar
    input logic clk,
    input logic rst,
    input logic [0:2] numero1
    input logic [0:2] numero2
    input logic a
    input logic b
    input logic c
    output logic igual
    output logic clk_out,
);
//Sincronizacion a 27 Mhz
    parameter int frecuencia = 27000000;
    parameter int freq_out = 10000;
    parameter int max_count = frecuencia / (2 * freq_out);

    logic [8:0] count;

    // Inicialización de variables
    always_ff @(posedge clk or posedge rst) begin
        if (rst) begin
            count <= 0;
            clk_out <= 0;
        end else begin
            if (count == max_count) begin
                clk_out <= ~clk_out;
                count <= 0;
            end else begin
                count <= count + 1;
            end
        end
    end
// Maquina de estado para el control de datos del teclado 
 
typedef enum logic [2:0] {SO, S1, S2} statetype;
statetype state, nextstate;
//stateregister 
always_ff@(posedge clk or posedge rst) begin
    if (rst) begin 
        state <= S0;
        //almacena el numero capturado en el teclado en el vector [2:0] numero1
    end else begin 
        state <= nextstate;
    end 
end 
//next state logic 
S0: if (a) nextstate=SO;
    else   nextstate=S1;
S1: if (b) nextstate=S2;
    else   nextstate=S0;
S2: if (c) nextstate=S0;
default: nextstate=S0
endcase 
// Output Logic
assign igual = (S0 + S1 == S2);

endmodule








//*****************************************



module capturador_de_teclas(
    input logic clk,
    input logic rst,
    input logic col_0, 
    input logic col_1, 
    input logic col_2, 
    input logic col_3,


    output logic [3:0]tecla_pre, 
    output logic suma,     
    output logic igual
);

    logic [3:0]fila_ent;
    logic clk_div;
    logic col_00;
    logic col_11;
    logic col_22;
    logic col_33;

    cont_anillo cont_ani_inst(
        .clk(clk),
        .rst(rst),
        .fila(fila_ent)
    );

    rebote rebote_ins0(
        .clk(clk),
        .boton(col_0),
        .boton_sal(col_00)
    );
        rebote rebote_ins1(
        .clk(clk),
        .boton(col_1),
        .boton_sal(col_11)
    );
        rebote rebote_ins2(
        .clk(clk),
        .boton(col_2),
        .boton_sal(col_22)
    );
        rebote rebote_ins3(
        .clk(clk),
        .boton(col_3),
        .boton_sal(col_33)
    );

    detector_columna detector_col_inst(
        .clk(clk),
        .rst(rst),
        .fila(fila_ent),
        .col_0(col_00),
        .col_1(col_11),
        .col_2(col_22),
        .col_3(col_33),
        .tecla_pre(tecla_pre),
        .suma(suma),
        .igual(igual)
    );

    divisor divisor_inst(
        .clk(clk),
        .clk_div(clk_div)
    );

endmodule





module cont_anillo(
    input logic clk,
    input logic rst,
    output logic [3:0]fila
);
logic [3:0]fila_encendida;

//Contador de anillo
    always_ff @(posedge clk or posedge rst)begin

        //Enciende la primera fila, para dar corriente.
        if (rst)begin
            fila_encendida <= 4'b0001;  
        end

        //Pasa a encender la siguiente fila cada nuevo ciclo del clock, se turna en activar las filas, para dar corriente.
        //Es un shifter, fila 1:0001 , fila 2: 0010 , fila 3: 0100, fila 4: 1000.
        else begin
            fila_encendida <= {fila_encendida[2:0], fila_encendida[3]};
        end
    end
    //Se le asigna la salida.
    assign fila = fila_encendida;
endmodule




module detector_columna (
    input logic clk,
    input logic rst,
    input logic [3:0]fila,  //entrada de contador de anillo;
    
    //entradas fisicas a FPGA
    input logic col_0, 
    input logic col_1, 
    input logic col_2, 
    input logic col_3, 

    output logic [3:0]tecla_pre,    //salida de teclas en bits
    output logic suma,         //salida de codigo de suma
    output logic igual        //salida de codigo de igual
);

    //se definen estados de la FSM
    typedef enum logic [4:0] { 
        F0, F1 , F2, F3, 
        F0C0, F0C1, F0C2, F0C3,
        F1C0, F1C1, F1C2, F1C3,
        F2C0, F2C1, F2C2, F2C3,
        F3C0, F3C1, F3C2, F3C3
    } estado;

    estado estado_act, estado_sig;
    logic [3:0] salida;


    //Para el estado actual
    always_ff @(posedge clk)begin
        if (rst)begin
            estado_act <= F0;
        end 
        else begin
            estado_act <= estado_sig;
        end
    end

    //Logica combinacional de la FSM, entre los estados
    always_comb begin
        estado_sig = estado_act; //Estado por defecto
        case(estado_act)

            //Primero verifica si la fila esta activa, si no pasa a la otra
            //Si esta activa, depende de cual col este activa, se da el siguiente estado
            F0: begin
                if(fila == 4'b0001) begin
                    if (col_0) estado_sig = F0C0; 
                    else if (col_1) estado_sig = F0C1;
                    else if (col_2) estado_sig = F0C2;
                    else if (col_3) estado_sig = F0C3;
                    else estado_sig = F1;
                end
                else begin 
                    estado_sig = F1;
                end
            end
            F1: begin
                if (fila == 4'b0010)begin
                    if (col_0) estado_sig = F1C0; 
                    else if (col_1) estado_sig = F1C1;
                    else if (col_2) estado_sig = F1C2;
                    else if (col_3) estado_sig = F1C3;
                    else estado_sig = F2;
                end
                else begin 
                    estado_sig = F2;
                end
            end
            F2: begin
                if(fila == 4'b0100) begin
                    if (col_0) estado_sig = F2C0;
                    else if (col_1) estado_sig = F2C1;
                    else if (col_2) estado_sig = F2C2;
                    else if (col_3) estado_sig = F2C3;
                    else estado_sig = F3;
                end
                else begin 
                    estado_sig = F3;
                end
            end
            F3: begin
                if (fila == 4'b1000)begin
                    if (col_0) estado_sig = F3C0;
                    else if (col_1) estado_sig = F3C1;
                    else if (col_2) estado_sig = F3C2;
                    else if (col_3) estado_sig = F3C3;
                    else estado_sig = F0;
                end
                else begin 
                    estado_sig = F0;
                end
            end
            default: estado_sig = F0;
        endcase     
    end 



    //Detectar estado y asignar codigo binario al estado para saber las teclas en binario
    always_ff @(posedge clk) begin 
        if (rst)begin 
            salida <= 4'b0000;
        end
        else begin
            case (estado_sig)
                F0C0: salida <= 4'b0000; //1
                F0C1: salida <= 4'b0001; //2
                F0C2: salida <= 4'b0010; //3
                F0C3: salida <= 4'b0011; //A
                F1C0: salida <= 4'b0100; //4
                F1C1: salida <= 4'b0101; //5
                F1C2: salida <= 4'b0110; //6
                F1C3: salida <= 4'b0111; //B
                F2C0: salida <= 4'b1000; //7
                F2C1: salida <= 4'b1001; //8
                F2C2: salida <= 4'b1010; //9
                F2C3: salida <= 4'b1011; //C
                F3C0: salida <= 4'b1100; //E
                F3C1: salida <= 4'b1101; //0
                F3C2: salida <= 4'b1110; //F
                F3C3: salida <= 4'b1111; //D
                default: salida <= 4'b0000;
            endcase
        end
    end
    
    //asigna la salida
    assign tecla_pre = salida;
    //se activa la suma
    assign suma= (tecla_pre == 4'b0011);
    //se activa el igual
    assign igual = (tecla_pre == 4'b0111);

endmodule





module divisor (
    input logic clk,
    output reg clk_div
);

    parameter frecuencia = 27000000; //27 Mhz
    parameter fre = 1000000; //1Mhz
    parameter max_cuenta = frecuencia / (2*fre); //13.5 ciclos aprox 

    reg [4:0]cuenta;

    initial begin 
        cuenta = 0;
        clk_div = 0;
    end

    always_ff @(posedge clk) begin 
        if (cuenta == max_cuenta) begin //la cantidad de ciclos en alto o bajo
            clk_div <= ~clk_div;
            cuenta <= 0;
        end
        else begin
            cuenta <= cuenta+1;

        end
    end

endmodule



module rebote(
    input logic clk,
    input logic boton,
    output logic boton_sal
); 
    logic clk_hab;
    //Salidas de FF D, Q2_com es el complemento.
    logic q1, q2, q2_com, q0;

    divisor clk_ha( clk, clk_hab);

    FF_D_habilitador ff1(clk, clk_hab, boton, q0);
    FF_D_habilitador ff2(clk, clk_hab, q0, q1);
    FF_D_habilitador ff3(clk, clk_hab, q1, q2);

    assign q2_com = ~q2;
    assign boton_sal = q1 & q2_com; //AND para salida
endmodule


//FF_D se actualiza cuando clk_hab esta en alto.
module FF_D_habilitador(
    input logic clk, 
    input logic clk_hab,
    input logic D, 
    output reg Q=0
);
    always_ff @ (posedge clk) begin
        if(clk_hab == 1) 
            Q <= D;
    end
endmodule 


//***************************************





/*Ocupamos:
Modulo #1
1. El escaneo de filas
2. Detección de columna, ya con esto se saca que tecla se preciosa
3. Eliminar el rebote mecánico 
Modulo #2
4. Luego sincronizarlo a 27MHz
5.
6. La maquina de estado
Modulo #3
7. Conversión del número a binario para la suma y los 7-segmentos
*/

Tarea 2/src/sim/divisor_tb.sv
`timescale 1ns/1ps

module divisor_tb;
    logic clk;
    logic clk_div;

    divisor divisor_tbb(
        .clk(clk),
        .clk_div(clk_div)
    );

    initial begin   

        clk = 0;
        forever begin
            #18.52 clk = ~clk;
        end
    end

    initial begin  
        $monitor("Tiempo: %0t | clk = %b | clk_div = %b", $time, clk, clk_div);
        
        // Para el diagrama de tiempos
        $dumpfile("module_divisor_tb.vcd");
        $dumpvars(0, divisor_tb); // Nombre correcto del testbench
    
        #10000 $finish;
    end


    

endmodule

Tarea 2/src/build/module_divisor_tb.vcd
$date
	Mon Sep 30 18:31:53 2024
$end
$version
	Icarus Verilog
$end
$timescale
	1ps
$end
$scope module divisor_tb $end
$var wire 1 ! clk_div $end
$var reg 1 " clk $end
$scope module divisor_tbb $end
$var wire 1 " clk $end
$var parameter 32 # fre $end
$var parameter 32 $ frecuencia $end
$var parameter 64 % max_cuenta $end
$var reg 1 ! clk_div $end
$var reg 5 & cuenta [4:0] $end
$upscope $end
$upscope $end
$enddefinitions $end
$comment Show the parameter values. $end
$dumpall
b1101 %
b1100110111111110011000000 $
b11110100001001000000 #
$end
#0
$dumpvars
b0 &
0"
0!
$end
#18520
b1 &
1"
#37040
0"
#55560
b10 &
1"
#74080
0"
#92600
b11 &
1"
#111120
0"
#129640
b100 &
1"
#148160
0"
#166680
b101 &
1"
#185200
0"
#203720
b110 &
1"
#222240
0"
#240760
b111 &
1"
#259280
0"
#277800
b1000 &
1"
#296320
0"
#314840
b1001 &
1"
#333360
0"
#351880
b1010 &
1"
#370400
0"
#388920
b1011 &
1"
#407440
0"
#425960
b1100 &
1"
#444480
0"
#463000
b1101 &
1"
#481520
0"
#500040
b0 &
1!
1"
#518560
0"
#537080
b1 &
1"
#555600
0"
#574120
b10 &
1"
#592640
0"
#611160
b11 &
1"
#629680
0"
#648200
b100 &
1"
#666720
0"
#685240
b101 &
1"
#703760
0"
#722280
b110 &
1"
#740800
0"
#759320
b111 &
1"
#777840
0"
#796360
b1000 &
1"
#814880
0"
#833400
b1001 &
1"
#851920
0"
#870440
b1010 &
1"
#888960
0"
#907480
b1011 &
1"
#926000
0"
#944520
b1100 &
1"
#963040
0"
#981560
b1101 &
1"
#1000080
0"
#1018600
b0 &
0!
1"
#1037120
0"
#1055640
b1 &
1"
#1074160
0"
#1092680
b10 &
1"
#1111200
0"
#1129720
b11 &
1"
#1148240
0"
#1166760
b100 &
1"
#1185280
0"
#1203800
b101 &
1"
#1222320
0"
#1240840
b110 &
1"
#1259360
0"
#1277880
b111 &
1"
#1296400
0"
#1314920
b1000 &
1"
#1333440
0"
#1351960
b1001 &
1"
#1370480
0"
#1389000
b1010 &
1"
#1407520
0"
#1426040
b1011 &
1"
#1444560
0"
#1463080
b1100 &
1"
#1481600
0"
#1500120
b1101 &
1"
#1518640
0"
#1537160
b0 &
1!
1"
#1555680
0"
#1574200
b1 &
1"
#1592720
0"
#1611240
b10 &
1"
#1629760
0"
#1648280
b11 &
1"
#1666800
0"
#1685320
b100 &
1"
#1703840
0"
#1722360
b101 &
1"
#1740880
0"
#1759400
b110 &
1"
#1777920
0"
#1796440
b111 &
1"
#1814960
0"
#1833480
b1000 &
1"
#1852000
0"
#1870520
b1001 &
1"
#1889040
0"
#1907560
b1010 &
1"
#1926080
0"
#1944600
b1011 &
1"
#1963120
0"
#1981640
b1100 &
1"
#2000160
0"
#2018680
b1101 &
1"
#2037200
0"
#2055720
b0 &
0!
1"
#2074240
0"
#2092760
b1 &
1"
#2111280
0"
#2129800
b10 &
1"
#2148320
0"
#2166840
b11 &
1"
#2185360
0"
#2203880
b100 &
1"
#2222400
0"
#2240920
b101 &
1"
#2259440
0"
#2277960
b110 &
1"
#2296480
0"
#2315000
b111 &
1"
#2333520
0"
#2352040
b1000 &
1"
#2370560
0"
#2389080
b1001 &
1"
#2407600
0"
#2426120
b1010 &
1"
#2444640
0"
#2463160
b1011 &
1"
#2481680
0"
#2500200
b1100 &
1"
#2518720
0"
#2537240
b1101 &
1"
#2555760
0"
#2574280
b0 &
1!
1"
#2592800
0"
#2611320
b1 &
1"
#2629840
0"
#2648360
b10 &
1"
#2666880
0"
#2685400
b11 &
1"
#2703920
0"
#2722440
b100 &
1"
#2740960
0"
#2759480
b101 &
1"
#2778000
0"
#2796520
b110 &
1"
#2815040
0"
#2833560
b111 &
1"
#2852080
0"
#2870600
b1000 &
1"
#2889120
0"
#2907640
b1001 &
1"
#2926160
0"
#2944680
b1010 &
1"
#2963200
0"
#2981720
b1011 &
1"
#3000240
0"
#3018760
b1100 &
1"
#3037280
0"
#3055800
b1101 &
1"
#3074320
0"
#3092840
b0 &
0!
1"
#3111360
0"
#3129880
b1 &
1"
#3148400
0"
#3166920
b10 &
1"
#3185440
0"
#3203960
b11 &
1"
#3222480
0"
#3241000
b100 &
1"
#3259520
0"
#3278040
b101 &
1"
#3296560
0"
#3315080
b110 &
1"
#3333600
0"
#3352120
b111 &
1"
#3370640
0"
#3389160
b1000 &
1"
#3407680
0"
#3426200
b1001 &
1"
#3444720
0"
#3463240
b1010 &
1"
#3481760
0"
#3500280
b1011 &
1"
#3518800
0"
#3537320
b1100 &
1"
#3555840
0"
#3574360
b1101 &
1"
#3592880
0"
#3611400
b0 &
1!
1"
#3629920
0"
#3648440
b1 &
1"
#3666960
0"
#3685480
b10 &
1"
#3704000
0"
#3722520
b11 &
1"
#3741040
0"
#3759560
b100 &
1"
#3778080
0"
#3796600
b101 &
1"
#3815120
0"
#3833640
b110 &
1"
#3852160
0"
#3870680
b111 &
1"
#3889200
0"
#3907720
b1000 &
1"
#3926240
0"
#3944760
b1001 &
1"
#3963280
0"
#3981800
b1010 &
1"
#4000320
0"
#4018840
b1011 &
1"
#4037360
0"
#4055880
b1100 &
1"
#4074400
0"
#4092920
b1101 &
1"
#4111440
0"
#4129960
b0 &
0!
1"
#4148480
0"
#4167000
b1 &
1"
#4185520
0"
#4204040
b10 &
1"
#4222560
0"
#4241080
b11 &
1"
#4259600
0"
#4278120
b100 &
1"
#4296640
0"
#4315160
b101 &
1"
#4333680
0"
#4352200
b110 &
1"
#4370720
0"
#4389240
b111 &
1"
#4407760
0"
#4426280
b1000 &
1"
#4444800
0"
#4463320
b1001 &
1"
#4481840
0"
#4500360
b1010 &
1"
#4518880
0"
#4537400
b1011 &
1"
#4555920
0"
#4574440
b1100 &
1"
#4592960
0"
#4611480
b1101 &
1"
#4630000
0"
#4648520
b0 &
1!
1"
#4667040
0"
#4685560
b1 &
1"
#4704080
0"
#4722600
b10 &
1"
#4741120
0"
#4759640
b11 &
1"
#4778160
0"
#4796680
b100 &
1"
#4815200
0"
#4833720
b101 &
1"
#4852240
0"
#4870760
b110 &
1"
#4889280
0"
#4907800
b111 &
1"
#4926320
0"
#4944840
b1000 &
1"
#4963360
0"
#4981880
b1001 &
1"
#5000400
0"
#5018920
b1010 &
1"
#5037440
0"
#5055960
b1011 &
1"
#5074480
0"
#5093000
b1100 &
1"
#5111520
0"
#5130040
b1101 &
1"
#5148560
0"
#5167080
b0 &
0!
1"
#5185600
0"
#5204120
b1 &
1"
#5222640
0"
#5241160
b10 &
1"
#5259680
0"
#5278200
b11 &
1"
#5296720
0"
#5315240
b100 &
1"
#5333760
0"
#5352280
b101 &
1"
#5370800
0"
#5389320
b110 &
1"
#5407840
0"
#5426360
b111 &
1"
#5444880
0"
#5463400
b1000 &
1"
#5481920
0"
#5500440
b1001 &
1"
#5518960
0"
#5537480
b1010 &
1"
#5556000
0"
#5574520
b1011 &
1"
#5593040
0"
#5611560
b1100 &
1"
#5630080
0"
#5648600
b1101 &
1"
#5667120
0"
#5685640
b0 &
1!
1"
#5704160
0"
#5722680
b1 &
1"
#5741200
0"
#5759720
b10 &
1"
#5778240
0"
#5796760
b11 &
1"
#5815280
0"
#5833800
b100 &
1"
#5852320
0"
#5870840
b101 &
1"
#5889360
0"
#5907880
b110 &
1"
#5926400
0"
#5944920
b111 &
1"
#5963440
0"
#5981960
b1000 &
1"
#6000480
0"
#6019000
b1001 &
1"
#6037520
0"
#6056040
b1010 &
1"
#6074560
0"
#6093080
b1011 &
1"
#6111600
0"
#6130120
b1100 &
1"
#6148640
0"
#6167160
b1101 &
1"
#6185680
0"
#6204200
b0 &
0!
1"
#6222720
0"
#6241240
b1 &
1"
#6259760
0"
#6278280
b10 &
1"
#6296800
0"
#6315320
b11 &
1"
#6333840
0"
#6352360
b100 &
1"
#6370880
0"
#6389400
b101 &
1"
#6407920
0"
#6426440
b110 &
1"
#6444960
0"
#6463480
b111 &
1"
#6482000
0"
#6500520
b1000 &
1"
#6519040
0"
#6537560
b1001 &
1"
#6556080
0"
#6574600
b1010 &
1"
#6593120
0"
#6611640
b1011 &
1"
#6630160
0"
#6648680
b1100 &
1"
#6667200
0"
#6685720
b1101 &
1"
#6704240
0"
#6722760
b0 &
1!
1"
#6741280
0"
#6759800
b1 &
1"
#6778320
0"
#6796840
b10 &
1"
#6815360
0"
#6833880
b11 &
1"
#6852400
0"
#6870920
b100 &
1"
#6889440
0"
#6907960
b101 &
1"
#6926480
0"
#6945000
b110 &
1"
#6963520
0"
#6982040
b111 &
1"
#7000560
0"
#7019080
b1000 &
1"
#7037600
0"
#7056120
b1001 &
1"
#7074640
0"
#7093160
b1010 &
1"
#7111680
0"
#7130200
b1011 &
1"
#7148720
0"
#7167240
b1100 &
1"
#7185760
0"
#7204280
b1101 &
1"
#7222800
0"
#7241320
b0 &
0!
1"
#7259840
0"
#7278360
b1 &
1"
#7296880
0"
#7315400
b10 &
1"
#7333920
0"
#7352440
b11 &
1"
#7370960
0"
#7389480
b100 &
1"
#7408000
0"
#7426520
b101 &
1"
#7445040
0"
#7463560
b110 &
1"
#7482080
0"
#7500600
b111 &
1"
#7519120
0"
#7537640
b1000 &
1"
#7556160
0"
#7574680
b1001 &
1"
#7593200
0"
#7611720
b1010 &
1"
#7630240
0"
#7648760
b1011 &
1"
#7667280
0"
#7685800
b1100 &
1"
#7704320
0"
#7722840
b1101 &
1"
#7741360
0"
#7759880
b0 &
1!
1"
#7778400
0"
#7796920
b1 &
1"
#7815440
0"
#7833960
b10 &
1"
#7852480
0"
#7871000
b11 &
1"
#7889520
0"
#7908040
b100 &
1"
#7926560
0"
#7945080
b101 &
1"
#7963600
0"
#7982120
b110 &
1"
#8000640
0"
#8019160
b111 &
1"
#8037680
0"
#8056200
b1000 &
1"
#8074720
0"
#8093240
b1001 &
1"
#8111760
0"
#8130280
b1010 &
1"
#8148800
0"
#8167320
b1011 &
1"
#8185840
0"
#8204360
b1100 &
1"
#8222880
0"
#8241400
b1101 &
1"
#8259920
0"
#8278440
b0 &
0!
1"
#8296960
0"
#8315480
b1 &
1"
#8334000
0"
#8352520
b10 &
1"
#8371040
0"
#8389560
b11 &
1"
#8408080
0"
#8426600
b100 &
1"
#8445120
0"
#8463640
b101 &
1"
#8482160
0"
#8500680
b110 &
1"
#8519200
0"
#8537720
b111 &
1"
#8556240
0"
#8574760
b1000 &
1"
#8593280
0"
#8611800
b1001 &
1"
#8630320
0"
#8648840
b1010 &
1"
#8667360
0"
#8685880
b1011 &
1"
#8704400
0"
#8722920
b1100 &
1"
#8741440
0"
#8759960
b1101 &
1"
#8778480
0"
#8797000
b0 &
1!
1"
#8815520
0"
#8834040
b1 &
1"
#8852560
0"
#8871080
b10 &
1"
#8889600
0"
#8908120
b11 &
1"
#8926640
0"
#8945160
b100 &
1"
#8963680
0"
#8982200
b101 &
1"
#9000720
0"
#9019240
b110 &
1"
#9037760
0"
#9056280
b111 &
1"
#9074800
0"
#9093320
b1000 &
1"
#9111840
0"
#9130360
b1001 &
1"
#9148880
0"
#9167400
b1010 &
1"
#9185920
0"
#9204440
b1011 &
1"
#9222960
0"
#9241480
b1100 &
1"
#9260000
0"
#9278520
b1101 &
1"
#9297040
0"
#9315560
b0 &
0!
1"
#9334080
0"
#9352600
b1 &
1"
#9371120
0"
#9389640
b10 &
1"
#9408160
0"
#9426680
b11 &
1"
#9445200
0"
#9463720
b100 &
1"
#9482240
0"
#9500760
b101 &
1"
#9519280
0"
#9537800
b110 &
1"
#9556320
0"
#9574840
b111 &
1"
#9593360
0"
#9611880
b1000 &
1"
#9630400
0"
#9648920
b1001 &
1"
#9667440
0"
#9685960
b1010 &
1"
#9704480
0"
#9723000
b1011 &
1"
#9741520
0"
#9760040
b1100 &
1"
#9778560
0"
#9797080
b1101 &
1"
#9815600
0"
#9834120
b0 &
1!
1"
#9852640
0"
#9871160
b1 &
1"
#9889680
0"
#9908200
b10 &
1"
#9926720
0"
#9945240
b11 &
1"
#9963760
0"
#9982280
b100 &
1"
