Tarea 1/src/design/module_decoder.sv

// Modulo de conexion

module principal (
   input logic [3:0] Gray,
   input logic [3:0] bin,
   input logic btn_in, 
   output logic [3:0] Led,
   output logic pin_uni,
   output logic pin_dec,
   output logic a, b, c, d, e, f, g,  // Salidas para el 7 segmentos uniades
   output logic ad, bd, cd, dd, ed, fd, gd  // Salidas para el 7 segmentos de decenas
);

logic [3:0] bin_todos;

// Instancia
gray_to_binary g_to_b_inst (
   .Gray(Gray),
   .bin(bin_todos)
);

// Instancia
binary_leds b_to_l_inst (
   .bin(bin_todos),
   .Led(Led)
);

assign pin_uni = btn_in ? 1'b0 : 1'b1;
assign pin_dec = btn_in ? 1'b1 : 1'b0;


decodificador_siete decodificador_unidades_inst (
   .bin(bin_todos),
   .a(a), .b(b), .c(c), .d(d), .e(e), .f(f), .g(g)
);

// Control para mostrar el número 1 en las decenas cuando el botón esté presionado
decodificador_decenas decodificador_decenas_inst (
   .btn_in(btn_in),   
   .ad(ad), .bd(bd), .cd(cd), .dd(dd), .ed(ed), .fd(fd), .gd(gd)
);

endmodule


//4.1

 module gray_to_binary (
    input logic [3:0] Gray,
    output logic [3:0] bin   
 );

   logic b3, b2, b1, b0;

   assign b3 = Gray[3];
   assign b2 = b3 ^ Gray[2];
   assign b1 = b2 ^ Gray[1];
   assign b0 = b1 ^ Gray[0];

   assign bin = {b3,b2,b1,b0};

 endmodule

//4.2


module binary_leds (
    input logic [3:0]bin,
    output logic [3:0] Led
 );

   assign bin[3] = Led[3];
   assign bin[2] = Led[2];
   assign bin[1] = Led[1];
   assign bin[0] = Led[0];

 endmodule





//4.3

// Módulo del decodificador para 7 segmentos (unidades)
module decodificador_siete (
   input logic [3:0] bin,
   output logic a, b, c, d, e, f, g
);

   assign a = (~bin[1] & ~bin[3]) | (bin[1] & bin[3]) | bin[2] | bin[0];
   assign b = (~bin[0] & ~bin[1]) | (~bin[3]) | (bin[0] & bin[1]);
   assign c = (~bin[0]) | (bin[3]) | (bin[1]);
   assign d = (~bin[1] & ~bin[3]) | (~bin[0] & bin[1] & bin[3]) | (bin[0] & ~bin[1]) | (bin[0] & ~bin[3]);
   assign e = (~bin[1] & ~bin[3]) | (bin[0] & ~bin[1]);
   assign f = (~bin[0] & ~bin[1]) | (~bin[0] & bin[3]) | bin[2] | (~bin[1] & bin[3]);
   assign g = bin[2] | (~bin[0] & bin[3]) | (bin[0] & ~bin[3]) | (~bin[1] & bin[3]);

endmodule

// Módulo del decodificador para 7 segmentos (decenas)
module decodificador_decenas (
   input logic btn_in,
   output logic ad, bd, cd, dd, ed, fd, gd
);

   // Cuando el botón está presionado, se muestra el número 1
   assign ad = btn_in ? 1'b0 : 1'b1;
   assign bd = btn_in ? 1'b1 : 1'b0;
   assign cd = btn_in ? 1'b1 : 1'b0;
   assign dd = btn_in ? 1'b0 : 1'b1;
   assign ed = btn_in ? 1'b0 : 1'b1;
   assign fd = btn_in ? 1'b0 : 1'b1;
   assign gd = btn_in ? 1'b0 : 1'b1;

endmodule

Tarea 1/src/sim/module_leds_tb.sv
`timescale 1ns/1ps

module module_leds_tb ;
    logic [3:0] bin;
    logic [3:0] leds;



    binary_leds binary_leds_tb(
        .bin(bin),
        .Led(leds)
    );

    initial begin

        bin = 4'b0000; #10;
        bin = 4'b0001; #10;
        bin = 4'b0010; #10;
        bin = 4'b0011; #10;
        bin = 4'b0100; #10;
        bin = 4'b0101; #10;
        bin = 4'b0110; #10;
        bin = 4'b0111; #10;
        bin = 4'b1000; #10;
        bin = 4'b1001; #10;
        bin = 4'b1010; #10;
        bin = 4'b1011; #10;
        bin = 4'b1100; #10;
        bin = 4'b1101; #10;
        bin = 4'b1110; #10;
        bin = 4'b1111; #10;

    end

    initial begin
        $dumpfile("module_leds_tb.vcd");
        $dumpvars(0, module_leds_tb);
    end


endmodule

Tarea 1/src/build/module_leds_tb.vcd
$date
	Wed Aug 28 18:35:55 2024
$end
$version
	Icarus Verilog
$end
$timescale
	1ps
$end
$scope module module_leds_tb $end
$var wire 4 ! leds [3:0] $end
$var reg 4 " bin [3:0] $end
$scope module binary_leds_tb $end
$var wire 4 # bin [3:0] $end
$var reg 4 $ Led [3:0] $end
$upscope $end
$upscope $end
$enddefinitions $end
$comment Show the parameter values. $end
$dumpall
$end
#0
$dumpvars
bx $
bx #
b0 "
bx !
$end
#10
b1 "
#20
b10 "
#30
b11 "
#40
b100 "
#50
b101 "
#60
b110 "
#70
b111 "
#80
b1000 "
#90
b1001 "
#100
b1010 "
#110
b1011 "
#120
b1100 "
#130
b1101 "
#140
b1110 "
#150
b1111 "
