Tarea 1/src/design/module_decoder.sv

// Modulo de conexion
/*
module principal (
   input logic [3:0] GrayCode,

   output logic led3, led2, led1, led0
   //Anadir mas salidas, como la del 7-segmentos

);

   logic [3:0]bit;

   //Instancia
   gray_to_binary g_to_b_inst (
      .Gray(GrayCode),
      .bin(bit)
      
   );

   //Instancia
   binary_leds b_to_l_inst (
      .bit3(b3),
      .bit2(b2),
      .bit1(b1),
      .bit0(b0),
      .led3(led3),
      .led2(led2),
      .led1(led1),
      .led0(led0)
   );

endmodule
*/

//4.1

 module gray_to_binary (
    input logic [3:0] Gray,
    output logic [3:0] bin   
 );

   logic b3, b2, b1, b0;

   assign b3 = Gray[3];
   assign b2 = Gray[3] ^ Gray[2];
   assign b1 = Gray[2] ^ Gray[1];
   assign b0 = Gray[1] ^ Gray[0];

   assign bin = {b3,b2,b1,b0};

 endmodule



//4.2

/*
//Con una instancia toma los valores de los bits para los Leds.
module binary_leds (
    input logic [3:0]bin,
    output logic [3:0] Led

 );

   logic bit3, bit2, bit1, bit1;

   assign bit3 = led3;
   assign bit2 = led2;
   assign bit1 = led1;
   assign bit0 = led0;

 endmodule
*/




//4.3

Tarea 1/src/sim/module_gray_to_binary_tb.sv
`timescale 1ns/1ps

 module module_gray_to_binary_tb ;
    logic [3:0] Gray_Code;
    logic [3:0] bit_4;

    gray_to_binary gray_to_binary_inst(
        .Gray(Gray_Code),
        .bin(bit_4)
    );

    initial begin
        
        Gray_Code = 4'b0000; #10;
        Gray_Code = 4'b0001; #10;
        Gray_Code = 4'b0010; #10;
        Gray_Code = 4'b0011; #10;
        Gray_Code = 4'b0100; #10;
        Gray_Code = 4'b0101; #10;
        Gray_Code = 4'b0110; #10;
        Gray_Code = 4'b0111; #10;
        Gray_Code = 4'b1000; #10;
        Gray_Code = 4'b1001; #10;
        Gray_Code = 4'b1010; #10;
        Gray_Code = 4'b1011; #10;
        Gray_Code = 4'b1100; #10;
        Gray_Code = 4'b1101; #10;
        Gray_Code = 4'b1110; #10;
        Gray_Code = 4'b1111; #10;

    end


    initial begin
        $dumpfile("module_gray_to_binary_tb.vcd");
        $dumpvars(0, module_gray_to_binary_tb);
    end
    
 endmodule

Tarea 1/src/build/module_gray_to_binary_tb.vcd
$date
	Wed Aug 28 17:28:18 2024
$end
$version
	Icarus Verilog
$end
$timescale
	1ps
$end
$scope module module_gray_to_binary_tb $end
$var wire 4 ! bit_4 [3:0] $end
$var reg 4 " Gray_Code [3:0] $end
$scope module gray_to_binary_inst $end
$var wire 4 # Gray [3:0] $end
$var wire 1 $ b0 $end
$var wire 1 % b1 $end
$var wire 1 & b2 $end
$var wire 4 ' bin [3:0] $end
$var wire 1 ( b3 $end
$upscope $end
$upscope $end
$enddefinitions $end
$comment Show the parameter values. $end
$dumpall
$end
#0
$dumpvars
0(
b0 '
0&
0%
0$
b0 #
b0 "
b0 !
$end
#10000
b1 !
b1 '
1$
b1 "
b1 #
#20000
b11 !
b11 '
1%
b10 "
b10 #
#30000
b10 !
b10 '
0$
b11 "
b11 #
#40000
b110 !
b110 '
1&
b100 "
b100 #
#50000
b111 !
b111 '
1$
b101 "
b101 #
#60000
b101 !
b101 '
0%
b110 "
b110 #
#70000
b100 !
b100 '
0$
b111 "
b111 #
#80000
b1100 !
b1100 '
1(
b1000 "
b1000 #
#90000
b1101 !
b1101 '
1$
b1001 "
b1001 #
#100000
b1111 !
b1111 '
1%
b1010 "
b1010 #
#110000
b1110 !
b1110 '
0$
b1011 "
b1011 #
#120000
b1010 !
b1010 '
0&
b1100 "
b1100 #
#130000
b1011 !
b1011 '
1$
b1101 "
b1101 #
#140000
b1001 !
b1001 '
0%
b1110 "
b1110 #
#150000
b1000 !
b1000 '
0$
b1111 "
b1111 #
