Tarea 1/src/design/module_decoder.sv

// Modulo de conexion

module principal (
   input logic [3:0] Gray,
   input logic [3:0] bin,
   input logic btn_in, 
   output logic [3:0] Led,
   output logic pin_uni,
   output logic pin_dec,
   output logic a, b, c, d, e, f, g,  // Salidas para el 7 segmentos uniades
   output logic ad, bd, cd, dd, ed, fd, gd  // Salidas para el 7 segmentos de decenas
);

logic [3:0] bin_todos;

// Instancia
gray_to_binary g_to_b_inst (
   .Gray(Gray),
   .bin(bin_todos)
);

// Instancia
binary_leds b_to_l_inst (
   .bin(bin_todos),
   .Led(Led)
);

assign pin_uni = btn_in ? 1'b0 : 1'b1;
assign pin_dec = btn_in ? 1'b1 : 1'b0;


decodificador_siete decodificador_unidades_inst (
   .bin(bin_todos),
   .a(a), .b(b), .c(c), .d(d), .e(e), .f(f), .g(g)
);

// Control para mostrar el número 1 en las decenas cuando el botón esté presionado
decodificador_decenas decodificador_decenas_inst (
   .btn_in(btn_in),   
   .ad(ad), .bd(bd), .cd(cd), .dd(dd), .ed(ed), .fd(fd), .gd(gd)
);

endmodule


//4.1

 module gray_to_binary (
    input logic [3:0] Gray,
    output logic [3:0] bin   
 );

   logic b3, b2, b1, b0;

   assign b3 = Gray[3];
   assign b2 = b3 ^ Gray[2];
   assign b1 = b2 ^ Gray[1];
   assign b0 = b1 ^ Gray[0];

   assign bin = {b3,b2,b1,b0};

 endmodule

//4.2


module binary_leds (
    input logic [3:0]bin,
    output logic [3:0] Led
 );

   assign bin[3] = Led[3];
   assign bin[2] = Led[2];
   assign bin[1] = Led[1];
   assign bin[0] = Led[0];

 endmodule





//4.3

// Módulo del decodificador para 7 segmentos (unidades)
module decodificador_siete (
   input logic [3:0] bin,
   output logic a, b, c, d, e, f, g
);

   assign a = (~bin[1] & ~bin[3]) | (bin[1] & bin[3]) | bin[2] | bin[0];
   assign b = (~bin[0] & ~bin[1]) | (~bin[3]) | (bin[0] & bin[1]);
   assign c = (~bin[0]) | (bin[3]) | (bin[1]);
   assign d = (~bin[1] & ~bin[3]) | (~bin[0] & bin[1] & bin[3]) | (bin[0] & ~bin[1]) | (bin[0] & ~bin[3]);
   assign e = (~bin[1] & ~bin[3]) | (bin[0] & ~bin[1]);
   assign f = (~bin[0] & ~bin[1]) | (~bin[0] & bin[3]) | bin[2] | (~bin[1] & bin[3]);
   assign g = bin[2] | (~bin[0] & bin[3]) | (bin[0] & ~bin[3]) | (~bin[1] & bin[3]);

endmodule

// Módulo del decodificador para 7 segmentos (decenas)
module decodificador_decenas (
   input logic btn_in,
   output logic ad, bd, cd, dd, ed, fd, gd
);

   // Cuando el botón está presionado, se muestra el número 1
   assign ad = btn_in ? 1'b0 : 1'b1;
   assign bd = btn_in ? 1'b1 : 1'b0;
   assign cd = btn_in ? 1'b1 : 1'b0;
   assign dd = btn_in ? 1'b0 : 1'b1;
   assign ed = btn_in ? 1'b0 : 1'b1;
   assign fd = btn_in ? 1'b0 : 1'b1;
   assign gd = btn_in ? 1'b0 : 1'b1;

endmodule

Tarea 1/src/sim/module_gray_to_binary_tb.sv
`timescale 1ns/1ps

 module module_gray_to_binary_tb (
    input logic [3:0] Gray_Code,
    output logic [3:0] bit_4;
 );

    gray_to_binary gray_to_binary_inst(
        .Gray(Gray_Code),
        .bin(bit_4)
    );

    initial begin
        
        Gray_Code = 4`b0000; #10
        Gray_Code = 4`b0001; #10
        Gray_Code = 4`b0010; #10
        Gray_Code = 4`b0011; #10
        Gray_Code = 4`b0100; #10
        Gray_Code = 4`b0101; #10
        Gray_Code = 4`b0110; #10
        Gray_Code = 4`b0111; #10
        Gray_Code = 4`b1000; #10
        Gray_Code = 4`b1001; #10
        Gray_Code = 4`b1010; #10
        Gray_Code = 4`b1011; #10
        Gray_Code = 4`b1100; #10
        Gray_Code = 4`b1101; #10
        Gray_Code = 4`b1110; #10
        Gray_Code = 4`b1111; #10

    end


    initial begin
        $dumpfile("module_gray_to_binary_tb.vcd");
        $dumpfile(0, module_gray_to_binary_tb);
    end
    
 endmodule

Tarea 1/src/build/module_gray_to_binary_tb.vcd
$date
	Wed Aug 28 18:36:52 2024
$end
$version
	Icarus Verilog
$end
$timescale
	1ps
$end
$scope module module_gray_to_binary_tb $end
$var wire 4 ! bit_4 [3:0] $end
$var reg 4 " Gray_Code [3:0] $end
$scope module gray_to_binary_inst $end
$var wire 4 # Gray [3:0] $end
$var wire 1 $ b0 $end
$var wire 1 % b1 $end
$var wire 1 & b2 $end
$var wire 4 ' bin [3:0] $end
$var wire 1 ( b3 $end
$upscope $end
$upscope $end
$enddefinitions $end
$comment Show the parameter values. $end
$dumpall
$end
#0
$dumpvars
0(
b0 '
0&
0%
0$
b0 #
b0 "
b0 !
$end
#10000
b1 !
b1 '
1$
b1 "
b1 #
#20000
1%
b11 !
b11 '
1$
b10 "
b10 #
#30000
b10 !
b10 '
0$
b11 "
b11 #
#40000
1&
1%
b111 !
b111 '
1$
b100 "
b100 #
#50000
b110 !
b110 '
0$
b101 "
b101 #
#60000
0%
b100 !
b100 '
0$
b110 "
b110 #
#70000
b101 !
b101 '
1$
b111 "
b111 #
#80000
1%
1$
b1111 !
b1111 '
1(
b1000 "
b1000 #
#90000
b1110 !
b1110 '
0$
b1001 "
b1001 #
#100000
0%
b1100 !
b1100 '
0$
b1010 "
b1010 #
#110000
b1101 !
b1101 '
1$
b1011 "
b1011 #
#120000
0&
0%
b1000 !
b1000 '
0$
b1100 "
b1100 #
#130000
b1001 !
b1001 '
1$
b1101 "
b1101 #
#140000
1%
b1011 !
b1011 '
1$
b1110 "
b1110 #
#150000
b1010 !
b1010 '
0$
b1111 "
b1111 #
