Tarea 1/src/design/module_decoder.sv

// Modulo de conexion

module principal (
   input logic [3:0] Gray,
   input logic [3:0] bin,
   input logic btn_in, 
   output logic [3:0] Led,
   output logic pin_uni,
   output logic pin_dec,
   output logic a, b, c, d, e, f, g,  // Salidas para el 7 segmentos uniades
   output logic ad, bd, cd, dd, ed, fd, gd  // Salidas para el 7 segmentos de decenas
);

logic [3:0] bin_todos;

// Instancia
gray_to_binary g_to_b_inst (
   .Gray(Gray),
   .bin(bin_todos)
);

// Instancia
binary_leds b_to_l_inst (
   .bin(bin_todos),
   .Led(Led)
);

assign pin_uni = btn_in ? 1'b0 : 1'b1;
assign pin_dec = btn_in ? 1'b1 : 1'b0;


decodificador_siete decodificador_unidades_inst (
   .bin(bin_todos),
   .a(a), .b(b), .c(c), .d(d), .e(e), .f(f), .g(g)
);

// Control para mostrar el número 1 en las decenas cuando el botón esté presionado
decodificador_decenas decodificador_decenas_inst (
   .btn_in(btn_in),   
   .ad(ad), .bd(bd), .cd(cd), .dd(dd), .ed(ed), .fd(fd), .gd(gd)
);

endmodule


//4.1

 module gray_to_binary (
    input logic [3:0] Gray,
    output logic [3:0] bin   
 );

   logic b3, b2, b1, b0;

   assign b3 = Gray[3];
   assign b2 = b3 ^ Gray[2];
   assign b1 = b2 ^ Gray[1];
   assign b0 = b1 ^ Gray[0];

   assign bin = {b3,b2,b1,b0};

 endmodule

//4.2


module binary_leds (
    input logic [3:0]bin,
    output logic [3:0] Led
 );

   assign bin[3] = Led[3];
   assign bin[2] = Led[2];
   assign bin[1] = Led[1];
   assign bin[0] = Led[0];

 endmodule





//4.3

// Módulo del decodificador para 7 segmentos (unidades)
module decodificador_siete (
   input logic [3:0] bin,
   output logic a, b, c, d, e, f, g
);

   assign a = (~bin[1] & ~bin[3]) | (bin[1] & bin[3]) | bin[2] | bin[0];
   assign b = (~bin[0] & ~bin[1]) | (~bin[3]) | (bin[0] & bin[1]);
   assign c = (~bin[0]) | (bin[3]) | (bin[1]);
   assign d = (~bin[1] & ~bin[3]) | (~bin[0] & bin[1] & bin[3]) | (bin[0] & ~bin[1]) | (bin[0] & ~bin[3]);
   assign e = (~bin[1] & ~bin[3]) | (bin[0] & ~bin[1]);
   assign f = (~bin[0] & ~bin[1]) | (~bin[0] & bin[3]) | bin[2] | (~bin[1] & bin[3]);
   assign g = bin[2] | (~bin[0] & bin[3]) | (bin[0] & ~bin[3]) | (~bin[1] & bin[3]);

endmodule

// Módulo del decodificador para 7 segmentos (decenas)
module decodificador_decenas (
   input logic btn_in,
   output logic ad, bd, cd, dd, ed, fd, gd
);

   // Cuando el botón está presionado, se muestra el número 1
   assign ad = btn_in ? 1'b0 : 1'b1;
   assign bd = btn_in ? 1'b1 : 1'b0;
   assign cd = btn_in ? 1'b1 : 1'b0;
   assign dd = btn_in ? 1'b0 : 1'b1;
   assign ed = btn_in ? 1'b0 : 1'b1;
   assign fd = btn_in ? 1'b0 : 1'b1;
   assign gd = btn_in ? 1'b0 : 1'b1;

endmodule

Tarea 1/src/sim/module_deco_dece_tb.sv
`timescale 1ns/1ps

module deco_dece_tb;
   
   logic [3:0] bits;
   logic a, b, c, d, e, f, g;
   logic btn_in;
   logic ad, bd, cd, dd, ed, fd, gd;

    decodificador_siete deco_s_inst(
        .bin(bits),
        .a(a), .b(b), .c(c), .d(d), .e(e), .f(f), .g(g)
    );

    decodificador_decenas decodificador_decenas_inst(
        .btn_in(btn_in),
        .ad(ad), .bd(bd), .cd(cd), .dd(dd), .ed(ed), .fd(fd), .gd(gd)
    );

    initial begin

        bits = 4'b0000; 
        btn_in = 0;
        btn_in = 1; 
        btn_in = 0; 
        #10;

        bits = 4'b0001;
        btn_in = 0;
        btn_in = 1; 
        btn_in = 0; 
        #10;

        bits = 4'b0010; 
        btn_in = 0;
        btn_in = 1; 
        btn_in = 0; 
        #10;

        bits = 4'b0011;
        btn_in = 0;
        btn_in = 1; 
        btn_in = 0; 
        #10;

        bits = 4'b0100;
        btn_in = 0;
        btn_in = 1; 
        btn_in = 0; 
        #10;

        bits = 4'b0101;
        btn_in = 0;
        btn_in = 1; 
        btn_in = 0; 
        #10;

        bits = 4'b0110;
        btn_in = 0;
        btn_in = 1; 
        btn_in = 0; 
        #10;

        bits = 4'b0111; 
        btn_in = 0;
        btn_in = 1; 
        btn_in = 0; 
        #10;

        bits = 4'b1000; 
        btn_in = 0;
        btn_in = 1; 
        btn_in = 0; 
        #10;

        bits = 4'b1001; 
        btn_in = 0;
        btn_in = 1; 
        btn_in = 0; 
        #10;

        bits = 4'b1010; 
        btn_in = 0;
        btn_in = 1; 
        btn_in = 0; 
        #10;

        bits = 4'b1011; 
        btn_in = 0;
        btn_in = 1; 
        btn_in = 0; 
        #10;

        bits = 4'b1100; 
        btn_in = 0;
        btn_in = 1; 
        btn_in = 0; 
        #10;

        bits = 4'b1101; 
        btn_in = 0;
        btn_in = 1; 
        btn_in = 0; 
        #10;

        bits = 4'b1110; 
        btn_in = 0;
        btn_in = 1; 
        btn_in = 0; 
        #10;

        bits = 4'b1111; 
        btn_in = 0;
        btn_in = 1; 
        btn_in = 0; 
        #10;

        $finish;

    end

    initial begin
        $dumpfile("module_deco_dece_tb.vcd");
        $dumpvars(0, deco_dece_tb);
    end



endmodule

Tarea 1/src/build/module_deco_dece_tb.vcd
$date
	Wed Aug 28 23:09:01 2024
$end
$version
	Icarus Verilog
$end
$timescale
	1ps
$end
$scope module deco_dece_tb $end
$var wire 1 ! gd $end
$var wire 1 " g $end
$var wire 1 # fd $end
$var wire 1 $ f $end
$var wire 1 % ed $end
$var wire 1 & e $end
$var wire 1 ' dd $end
$var wire 1 ( d $end
$var wire 1 ) cd $end
$var wire 1 * c $end
$var wire 1 + bd $end
$var wire 1 , b $end
$var wire 1 - ad $end
$var wire 1 . a $end
$var reg 4 / bits [3:0] $end
$var reg 1 0 btn_in $end
$scope module deco_s_inst $end
$var wire 1 . a $end
$var wire 1 , b $end
$var wire 4 1 bin [3:0] $end
$var wire 1 * c $end
$var wire 1 ( d $end
$var wire 1 & e $end
$var wire 1 $ f $end
$var wire 1 " g $end
$upscope $end
$scope module decodificador_decenas_inst $end
$var wire 1 0 btn_in $end
$var wire 1 ! gd $end
$var wire 1 # fd $end
$var wire 1 % ed $end
$var wire 1 ' dd $end
$var wire 1 ) cd $end
$var wire 1 + bd $end
$var wire 1 - ad $end
$upscope $end
$upscope $end
$enddefinitions $end
$comment Show the parameter values. $end
$dumpall
$end
#0
$dumpvars
b0 1
00
b0 /
1.
1-
1,
0+
1*
0)
1(
1'
1&
1%
1$
1#
0"
1!
$end
#10000
0$
0*
1"
00
b1 /
b1 1
#20000
0.
0(
0&
0"
1*
00
b10 /
b10 1
#30000
1"
1(
1.
00
b11 /
b11 1
#40000
1&
1(
1$
1.
1*
00
b100 /
b100 1
#50000
0*
00
b101 /
b101 1
#60000
0(
0&
1*
00
b110 /
b110 1
#70000
1(
00
b111 /
b111 1
#80000
1,
0.
0(
1*
00
b1000 /
b1000 1
#90000
0,
1(
1&
1.
00
b1001 /
b1001 1
#100000
1(
1$
1"
0&
1.
00
b1010 /
b1010 1
#110000
0(
0$
0"
1,
00
b1011 /
b1011 1
#120000
1"
1,
1$
00
b1100 /
b1100 1
#130000
0,
1(
1&
00
b1101 /
b1101 1
#140000
1(
0&
00
b1110 /
b1110 1
#150000
0(
1,
00
b1111 /
b1111 1
