Tarea 1/src/design/module_decoder.sv

// Modulo de conexion
/*
module principal (
   input logic [3:0] GrayCode,

   output logic led3, led2, led1, led0
   //Anadir mas salidas, como la del 7-segmentos

);

   logic [3:0]bit;

   //Instancia
   gray_to_binary g_to_b_inst (
      .Gray(GrayCode),
      .bin(bit)
      
   );

   //Instancia
   binary_leds b_to_l_inst (
      .bit3(b3),
      .bit2(b2),
      .bit1(b1),
      .bit0(b0),
      .led3(led3),
      .led2(led2),
      .led1(led1),
      .led0(led0)
   );

endmodule
*/

//4.1

 module gray_to_binary (
    input logic [3:0] Gray,
    output logic [3:0] bin   
 );

   logic b3, b2, b1, b0;

   assign b3 = Gray[3];
   assign b2 = Gray[3] ^ Gray[2];
   assign b1 = Gray[2] ^ Gray[1];
   assign b0 = Gray[1] ^ Gray[0];

   assign bin = {b3,b2,b1,b0};

 endmodule



//4.2


module binary_leds (
    input logic [3:0]bin,
    output logic [3:0] Led
 );

   assign bin[3] = Led[3];
   assign bin[2] = Led[2];
   assign bin[1] = Led[1];
   assign bin[0] = Led[0];

 endmodule





//4.3

Tarea 1/src/sim/module_leds_tb.sv
`timescale 1ps/1ps

module module_leds_tb ;
    logic [3:0] bin;
    logic [3:0] leds;



    binary_leds binary_leds_tb(
        .bin(bin),
        .Led(leds)
    );

    initial begin

        bin = 4'b0000; #10;
        bin = 4'b0001; #10;
        bin = 4'b0010; #10;
        bin = 4'b0011; #10;
        bin = 4'b0100; #10;
        bin = 4'b0101; #10;
        bin = 4'b0110; #10;
        bin = 4'b0111; #10;
        bin = 4'b1000; #10;
        bin = 4'b1001; #10;
        bin = 4'b1010; #10;
        bin = 4'b1011; #10;
        bin = 4'b1100; #10;
        bin = 4'b1101; #10;
        bin = 4'b1110; #10;
        bin = 4'b1111; #10;

    end

    initial begin
        $dumpfile("module_leds_tb.vcd");
        $dumpvars(0, module_leds_tb);
    end


endmodule

Tarea 1/src/build/module_leds_tb.vcd
$date
	Wed Aug 28 18:12:15 2024
$end
$version
	Icarus Verilog
$end
$timescale
	1ps
$end
$scope module module_leds_tb $end
$var wire 4 ! leds [3:0] $end
$var reg 4 " bin [3:0] $end
$scope module binary_leds_tb $end
$var wire 4 # bin [3:0] $end
$var reg 4 $ Led [3:0] $end
$upscope $end
$upscope $end
$enddefinitions $end
$comment Show the parameter values. $end
$dumpall
$end
#0
$dumpvars
bx $
bx #
b0 "
bx !
$end
#10
b1 "
#20
b10 "
#30
b11 "
#40
b100 "
#50
b101 "
#60
b110 "
#70
b111 "
#80
b1000 "
#90
b1001 "
#100
b1010 "
#110
b1011 "
#120
b1100 "
#130
b1101 "
#140
b1110 "
#150
b1111 "
