Tarea 1/src/design/module_decoder.sv

// Modulo de conexion

module principal (
   input logic [3:0] Gray,
   input logic [3:0] bin,
   input logic btn_in, 
   output logic [3:0] Led,
   output logic pin_uni,
   output logic pin_dec,
   output logic a, b, c, d, e, f, g,  // Salidas para el 7 segmentos uniades
   output logic bd, cd  // Salidas para el 7 segmentos de decenas
);

logic [3:0] bin_todos;

// Instancia
gray_to_binary g_to_b_inst (
   .Gray(Gray),
   .bin(bin_todos)
);

// Instancia
binary_leds b_to_l_inst (
   .bin(bin_todos),
   .Led(Led)
);

assign pin_uni = btn_in ? 1'b0 : 1'b1;
assign pin_dec = btn_in ? 1'b1 : 1'b0;


decodificador_siete decodificador_unidades_inst (
   .bin(bin_todos),
   .a(a), .b(b), .c(c), .d(d), .e(e), .f(f), .g(g)
);

// Control para mostrar el número 1 en las decenas cuando el botón esté presionado
decodificador_decenas decodificador_decenas_inst (
   .btn_in(btn_in),   
   .bd(bd), .cd(cd)
);

endmodule


//4.1

 module gray_to_binary (
    input logic [3:0] Gray,
    output logic [3:0] bin   
 );

   logic b3, b2, b1, b0;

   assign b3 = Gray[3];
   assign b2 = b3 ^ Gray[2];
   assign b1 = b2 ^ Gray[1];
   assign b0 = b1 ^ Gray[0];

   assign bin = {b3,b2,b1,b0};

 endmodule

//4.2


module binary_leds (
    input logic [3:0]bin,
    output logic [3:0] Led
 );

   assign bin[3] = Led[3];
   assign bin[2] = Led[2];
   assign bin[1] = Led[1];
   assign bin[0] = Led[0];

 endmodule





//4.3

// Módulo del decodificador para 7 segmentos (unidades)
module decodificador_siete (
   input logic [3:0] bin,
   output logic a, b, c, d, e, f, g
);

   assign a = (~bin[1] & ~bin[3]) | (bin[1] & bin[3]) | bin[2] | bin[0];
   assign b = (~bin[0] & ~bin[1]) | (~bin[3]) | (bin[0] & bin[1]);
   assign c = (~bin[0]) | (bin[3]) | (bin[1]);
   assign d = (~bin[1] & ~bin[3]) | (~bin[0] & bin[1] & bin[3]) | (bin[0] & ~bin[1]) | (bin[0] & ~bin[3]);
   assign e = (~bin[1] & ~bin[3]) | (bin[0] & ~bin[1]);
   assign f = (~bin[0] & ~bin[1]) | (~bin[0] & bin[3]) | bin[2] | (~bin[1] & bin[3]);
   assign g = bin[2] | (~bin[0] & bin[3]) | (bin[0] & ~bin[3]) | (~bin[1] & bin[3]);

endmodule

// Módulo del decodificador para 7 segmentos (decenas)
module decodificador_decenas (
   input logic btn_in,
   output logic bd, cd
);

   // Cuando el botón está presionado, se muestra el número 1
   assign bd = btn_in ? 1'b1 : 1'b0;
   assign cd = btn_in ? 1'b1 : 1'b0;


endmodule

Tarea 1/src/sim/module_principal_tb.sv
`timescale 1ns/1ps

module principal_tb;
    logic [3:0] gray;
    logic [3:0] bit_4;
    logic [3:0] leds;
    logic a, b, c, d, e, f, g;
    logic btn_in;
    logic bd, cd;


    gray_to_binary g_t_inst (
        .Gray(gray),
        .bin(bit_4)
    );

    binary_leds b_l_inst (
        .bin(bit_4),
        .Led(leds)
    );

    decodificador_siete d_s_inst(
        .bin(bit_4),
        .a(a), .b(b), .c(c), .d(d), .e(e), .f(f), .g(g)
    );

    decodificador_decenas d_d_inst(
        .btn_in(btn_in),
        .bd(bd), .cd(cd)
    );





    initial begin

        gray = 4'b0000; #10;
        gray = 4'b0001; #10;
        gray = 4'b0010; #10;
        gray = 4'b0011; #10;
        gray = 4'b0100; #10;
        gray = 4'b0101; #10;
        gray = 4'b0110; #10;
        gray = 4'b0111; #10;
        gray = 4'b1000; #10;
        gray = 4'b1001; #10;
        gray = 4'b1010; #10;
        gray = 4'b1011; #10;
        gray = 4'b1100; #10;
        gray = 4'b1101; #10;
        gray = 4'b1110; #10;
        gray = 4'b1111; #10;


        $finish;

    end



    initial begin
        $dumpfile("module_principal_tb.vcd");
        $dumpvars(0, principal_tb);
    end

endmodule

Tarea 1/src/build/module_principal_tb.vcd
$date
	Sat Aug 31 11:07:59 2024
$end
$version
	Icarus Verilog
$end
$timescale
	1ps
$end
$scope module principal_tb $end
$var wire 4 ! leds [3:0] $end
$var wire 1 " g $end
$var wire 1 # f $end
$var wire 1 $ e $end
$var wire 1 % d $end
$var wire 1 & cd $end
$var wire 1 ' c $end
$var wire 4 ( bit_4 [3:0] $end
$var wire 1 ) bd $end
$var wire 1 * b $end
$var wire 1 + a $end
$var reg 1 , btn_in $end
$var reg 4 - gray [3:0] $end
$scope module b_l_inst $end
$var wire 4 . bin [3:0] $end
$var reg 4 / Led [3:0] $end
$upscope $end
$scope module d_d_inst $end
$var wire 1 , btn_in $end
$var wire 1 & cd $end
$var wire 1 ) bd $end
$upscope $end
$scope module d_s_inst $end
$var wire 1 + a $end
$var wire 1 * b $end
$var wire 1 ' c $end
$var wire 1 % d $end
$var wire 1 $ e $end
$var wire 1 # f $end
$var wire 1 " g $end
$var wire 4 0 bin [3:0] $end
$upscope $end
$scope module g_t_inst $end
$var wire 4 1 Gray [3:0] $end
$var wire 1 2 b0 $end
$var wire 1 3 b1 $end
$var wire 1 4 b2 $end
$var wire 4 5 bin [3:0] $end
$var wire 1 6 b3 $end
$upscope $end
$upscope $end
$enddefinitions $end
$comment Show the parameter values. $end
$dumpall
$end
#0
$dumpvars
06
b0 5
04
03
02
b0 1
b0 0
bx /
bx .
b0 -
x,
1+
1*
x)
b0 (
1'
x&
1%
1$
1#
0"
bx !
$end
#10000
0#
1"
0'
b1 (
b1 0
b1 5
12
b1 -
b1 1
#20000
0$
1"
1'
13
b11 (
b11 0
b11 5
12
b10 -
b10 1
#30000
0"
0%
0+
b10 (
b10 0
b10 5
02
b11 -
b11 1
#40000
0$
1"
1#
1%
1+
14
13
b111 (
b111 0
b111 5
12
b100 -
b100 1
#50000
0%
b110 (
b110 0
b110 5
02
b101 -
b101 1
#60000
1$
1'
1%
03
b100 (
b100 0
b100 5
02
b110 -
b110 1
#70000
0'
b101 (
b101 0
b101 5
12
b111 -
b111 1
#80000
0%
0$
1'
13
12
b1111 (
b1111 0
b1111 5
16
b1000 -
b1000 1
#90000
1%
0*
b1110 (
b1110 0
b1110 5
02
b1001 -
b1001 1
#100000
1*
0%
03
b1100 (
b1100 0
b1100 5
02
b1010 -
b1010 1
#110000
0*
1%
1$
b1101 (
b1101 0
b1101 5
12
b1011 -
b1011 1
#120000
1*
0+
1"
0%
1#
0$
04
03
b1000 (
b1000 0
b1000 5
02
b1100 -
b1100 1
#130000
0*
1%
1$
1+
b1001 (
b1001 0
b1001 5
12
b1101 -
b1101 1
#140000
1*
0"
0#
0%
0$
1+
13
b1011 (
b1011 0
b1011 5
12
b1110 -
b1110 1
#150000
1%
1"
1#
0*
b1010 (
b1010 0
b1010 5
02
b1111 -
b1111 1
